[
  {
    "id": "pj7zy9",
    "name": "Трасса-М8-1",
    "geo": {
      "latitude": 42.0577946280053,
      "longitude": 60.98345108021445
    }
  },
  {
    "id": "rzuuta",
    "name": "Трасса-М8-2",
    "geo": {
      "latitude": 42.04911214790408,
      "longitude": 60.990001694227885
    }
  },
  {
    "id": "y2q3a8",
    "name": "Шиловская-3",
    "geo": {
      "latitude": 42.04332382783659,
      "longitude": 60.9967068763647
    }
  },
  {
    "id": "3e8zky",
    "name": "Шиловская-4",
    "geo": {
      "latitude": 42.04171596115137,
      "longitude": 61.00574883385906
    }
  },
  {
    "id": "1aq5me",
    "name": "Шиловская-5",
    "geo": {
      "latitude": 42.04461012118509,
      "longitude": 61.013697393738425
    }
  },
  {
    "id": "t6u7kb",
    "name": "Погореловская-6",
    "geo": {
      "latitude": 42.048469001230046,
      "longitude": 61.020864976172675
    }
  },
  {
    "id": "a2c5eh",
    "name": "Вельск_7",
    "geo": {
      "latitude": 42.056508334657025,
      "longitude": 61.032703522726536
    }
  },
  {
    "id": "w2k7b3",
    "name": "Вельск_8",
    "geo": {
      "latitude": 42.04332382783659,
      "longitude": 61.04033392773769
    }
  },
  {
    "id": "3iayym",
    "name": "Вельск_9",
    "geo": {
      "latitude": 42.028853027667935,
      "longitude": 61.04920780326492
    }
  },
  {
    "id": "lmkzsd",
    "name": "Вельск_10",
    "geo": {
      "latitude": 42.01824110754421,
      "longitude": 61.06321412889176
    }
  },
  {
    "id": "c0n0lh",
    "name": "Вельск_11",
    "geo": {
      "latitude": 42.025637294297184,
      "longitude": 61.076747692740696
    }
  },
  {
    "id": "mgn45x",
    "name": "Вельск_12",
    "geo": {
      "latitude": 42.033998201061394,
      "longitude": 61.084989443029514
    }
  },
  {
    "id": "r7hi9u",
    "name": "Тарасовская_13",
    "geo": {
      "latitude": 42.04589641453336,
      "longitude": 61.0912082111052
    }
  },
  {
    "id": "bzzy01",
    "name": "Тарасовская_14",
    "geo": {
      "latitude": 42.054578894634545,
      "longitude": 61.10379747379329
    }
  },
  {
    "id": "9mzooj",
    "name": "Вельск_15",
    "geo": {
      "latitude": 42.07162228149997,
      "longitude": 61.11265358142734
    }
  },
  {
    "id": "46lrj3",
    "name": "Вельск_16",
    "geo": {
      "latitude": 42.09638342845511,
      "longitude": 61.12306022099892
    }
  },
  {
    "id": "i2wrmb",
    "name": "Вельск_17",
    "geo": {
      "latitude": 42.11889356205097,
      "longitude": 61.126787138997
    }
  },
  {
    "id": "cr8xq3",
    "name": "Вельск_18",
    "geo": {
      "latitude": 42.14622729570286,
      "longitude": 61.127718799809855
    }
  },
  {
    "id": "72er84",
    "name": "Вельск_19",
    "geo": {
      "latitude": 42.18127878944469,
      "longitude": 61.127718799809855
    }
  },
  {
    "id": "kri6ym",
    "name": "Вельск_20",
    "geo": {
      "latitude": 42.19446329626513,
      "longitude": 61.13920702440845
    }
  },
  {
    "id": "lrp774",
    "name": "Вельск_21",
    "geo": {
      "latitude": 42.21504398983831,
      "longitude": 61.16139540543128
    }
  }
]